setup.py
dsnd_han_probability/Binomialdistribution.py
dsnd_han_probability/Gaussiandistribution.py
dsnd_han_probability/Generaldistribution.py
dsnd_han_probability/__init__.py
dsnd_han_probability.egg-info/PKG-INFO
dsnd_han_probability.egg-info/SOURCES.txt
dsnd_han_probability.egg-info/dependency_links.txt
dsnd_han_probability.egg-info/not-zip-safe
dsnd_han_probability.egg-info/top_level.txt