Metadata-Version: 1.0
Name: dsnd-han-probability
Version: 0.5
Summary: Gaussian and Binomial distributions
Home-page: UNKNOWN
Author: Jing Han Ng
Author-email: UNKNOWN
License: UNKNOWN
Platform: UNKNOWN
